tkinterflow/__init__.py
tkinterflow/tkinterflow.py
tkinterflow-0.0.5.dist-info/LICENSE
tkinterflow-0.0.5.dist-info/METADATA
tkinterflow-0.0.5.dist-info/WHEEL
tkinterflow-0.0.5.dist-info/top_level.txt
tkinterflow-0.0.5.dist-info/RECORD
