Metadata-Version: 2.1
Name: tkinterflow
Version: 0.0.5
Summary: This package adds a .flow to existing .pack, .grid, and .place geometry managers.
Home-page: https://github.com/garydavenport73/tkinterflow
Author: Gary Davenport
Author-email: dovedweller@gmail.com
License: UNKNOWN
Project-URL: Bug Tracker, https://github.com/garydavenport73/tkinterflow/issues
Platform: UNKNOWN
Classifier: Programming Language :: Python :: 3
Classifier: License :: OSI Approved :: MIT License
Classifier: Operating System :: OS Independent
Requires-Python: >=3.6
License-File: LICENSE
